README.rst
setup.py
django_rql_filter.egg-info/PKG-INFO
django_rql_filter.egg-info/SOURCES.txt
django_rql_filter.egg-info/dependency_links.txt
django_rql_filter.egg-info/requires.txt
django_rql_filter.egg-info/top_level.txt
rql_filter/__init__.py
rql_filter/backend.py
rql_filter/parser/__init__.py
rql_filter/parser/parser.py
rql_filter/parser/semantics.py