Metadata-Version: 1.1
Name: django-rql-filter
Version: 0.1.3
Summary: A RQL-enabled filter backend for django-rest-framework
Home-page: https://github.com/njoyard/django-rql-filter
Author: Nicolas Joyard
Author-email: joyard.nicolas@gmail.com
License: MIT
Keywords: django filter drf rest rql rsql fiql
Platform: UNKNOWN
Classifier: Development Status :: 3 - Alpha
Classifier: Framework :: Django
Classifier: Intended Audience :: Developers
Classifier: License :: OSI Approved :: MIT License
